{
  "MemLists": {
    "ru": "MemLists",
    "ua": "MemLists"
  },
  "Welcome": {
    "ru": "Добро пожаловать",
    "ua": "Ласкаво просимо"
  },
  "Welcome to MemLists": {
    "ru": "Добро пожаловать в MemLists",
    "ua": "Ласкаво просимо до MemLists"
  },
  "Combined memos and universal lists": {
    "ru": "Объединенные заметки и универсальные списки",
    "ua": "Об'єднані нотатки та універсальні списки"
  },
  "Choose language": {
    "ru": "Выберите язык",
    "ua": "Оберіть мову"
  },
  "Choose theme": {
    "ru": "Выберите тему",
    "ua": "Оберіть тему"
  },
  "Start": {
    "ru": "Начать",
    "ua": "Почати"
  },
  "English": {
    "ru": "Английский",
    "ua": "Англійська"
  },
  "Russian": {
    "ru": "Русский",
    "ua": "Російська"
  },
  "Ukrainian": {
    "ru": "Украинский",
    "ua": "Українська"
  },
  "Light": {
    "ru": "Светлая",
    "ua": "Світла"
  },
  "Dark": {
    "ru": "Темная",
    "ua": "Темна"
  },
  "Blue": {
    "ru": "Синяя",
    "ua": "Синя"
  },
  "Green": {
    "ru": "Зеленая",
    "ua": "Зелена"
  },
  "Memos": {
    "ru": "Заметки",
    "ua": "Нотатки"
  },
  "New memo": {
    "ru": "Новая заметка",
    "ua": "Нова нотатка"
  },
  "NewItem": {
    "ru": "Новый элемент",
    "ua": "Новий елемент"
  },
  "New list": {
    "ru": "Новый список",
    "ua": "Новий список"
  },
  "New folder": {
    "ru": "Новая папка",
    "ua": "Нова папка"
  },
  "New item": {
    "ru": "Новый элемент",
    "ua": "Новий елемент"
  },
  "Lists": {
    "ru": "Списки",
    "ua": "Списки"
  },
  "Settings": {
    "ru": "Настройки",
    "ua": "Налаштування"
  },
  "Back": {
    "ru": "Назад",
    "ua": "Назад"
  },
  "Main screen": {
    "ru": "Главный экран",
    "ua": "Головний екран"
  },
  "Folders": {
    "ru": "Папки",
    "ua": "Папки"
  },
  "Shared settings": {
    "ru": "Общие настройки",
    "ua": "Спільні налаштування"
  },
  "Open Lists": {
    "ru": "Открыть списки",
    "ua": "Відкрити списки"
  },
  "Open settings": {
    "ru": "Открыть настройки",
    "ua": "Відкрити налаштування"
  },
  "Menu": {
    "ru": "Меню",
    "ua": "Меню"
  },
  "(All)": {
    "ru": "(Все)",
    "ua": "(Усі)"
  },
  "Check Reminders": {
    "ru": "Проверить напоминания",
    "ua": "Перевірити нагадування"
  },
  "Clear All Filters": {
    "ru": "Сбросить все фильтры",
    "ua": "Скинути всі фільтри"
  },
  "Filters": {
    "ru": "Фильтры",
    "ua": "Фільтри"
  },
  "Tag Filter": {
    "ru": "Фильтр тегов",
    "ua": "Фільтр тегів"
  },
  "About": {
    "ru": "О программе",
    "ua": "Про програму"
  },
  "Version": {
    "ru": "Версия",
    "ua": "Версія"
  },
  "Build": {
    "ru": "Сборка",
    "ua": "Збірка"
  },
  "Author": {
    "ru": "Автор",
    "ua": "Автор"
  },
  "OK": {
    "ru": "OK",
    "ua": "OK"
  },
  "Open dictionary": {
    "ru": "Открыть словарь",
    "ua": "Відкрити словник"
  },
  "Items dictionary": {
    "ru": "Словарь элементов",
    "ua": "Словник елементів"
  },
  "Folders and lists": {
    "ru": "Папки и списки",
    "ua": "Папки та списки"
  },
  "No lists yet": {
    "ru": "Списков пока нет",
    "ua": "Списків поки немає"
  },
  "The lists home is empty.": {
    "ru": "Главный экран списков пока пуст.",
    "ua": "Головний екран списків поки порожній."
  },
  "No items yet": {
    "ru": "Элементов пока нет",
    "ua": "Елементів поки немає"
  },
  "The memos list is empty.": {
    "ru": "Список заметок пока пуст.",
    "ua": "Список нотаток поки порожній."
  },
  "Add later from the Lists module": {
    "ru": "Добавить можно позже в модуле списков",
    "ua": "Додати можна пізніше в модулі списків"
  },
  "Loading memos": {
    "ru": "Загрузка заметок",
    "ua": "Завантаження нотаток"
  },
  "Loading lists": {
    "ru": "Загрузка списков",
    "ua": "Завантаження списків"
  },
  "General": {
    "ru": "Общие",
    "ua": "Загальні"
  },
  "Reminders": {
    "ru": "Напоминания",
    "ua": "Нагадування"
  },
  "Reminder": {
    "ru": "Напоминание",
    "ua": "Нагадування"
  },
  "Active": {
    "ru": "Активно",
    "ua": "Активно"
  },
  "Language": {
    "ru": "Язык",
    "ua": "Мова"
  },
  "Theme": {
    "ru": "Тема",
    "ua": "Тема"
  },
  "Priority": {
    "ru": "Приоритет",
    "ua": "Пріоритет"
  },
  "Title": {
    "ru": "Заголовок",
    "ua": "Заголовок"
  },
  "Name": {
    "ru": "Название",
    "ua": "Назва"
  },
  "Content": {
    "ru": "Текст",
    "ua": "Текст"
  },
  "Comment": {
    "ru": "Комментарий",
    "ua": "Коментар"
  },
  "Date": {
    "ru": "Дата",
    "ua": "Дата"
  },
  "Quantity": {
    "ru": "Количество",
    "ua": "Кількість"
  },
  "Unit": {
    "ru": "Единица",
    "ua": "Одиниця"
  },
  "Newest first": {
    "ru": "Сначала новые",
    "ua": "Спочатку нові"
  },
  "Enable reminders": {
    "ru": "Включить напоминания",
    "ua": "Увімкнути нагадування"
  },
  "Auto-sort dictionary": {
    "ru": "Автосортировка словаря",
    "ua": "Автосортування словника"
  },
  "Keep screen on": {
    "ru": "Не выключать экран",
    "ua": "Не вимикати екран"
  },
  "Tags": {
    "ru": "Теги",
    "ua": "Теги"
  },
  "Save memo": {
    "ru": "Сохранить заметку",
    "ua": "Зберегти нотатку"
  },
  "Save": {
    "ru": "Сохранить",
    "ua": "Зберегти"
  },
  "Save list": {
    "ru": "Сохранить список",
    "ua": "Зберегти список"
  },
  "Save folder": {
    "ru": "Сохранить папку",
    "ua": "Зберегти папку"
  },
  "Save item": {
    "ru": "Сохранить элемент",
    "ua": "Зберегти елемент"
  },
  "Title is required": {
    "ru": "Заголовок обязателен",
    "ua": "Заголовок обов'язковий"
  },
  "Name is required": {
    "ru": "Название обязательно",
    "ua": "Назва обов'язкова"
  },
  "Date format is invalid": {
    "ru": "Формат даты неверен",
    "ua": "Формат дати неправильний"
  },
  "Use YYYYMMDD or leave empty": {
    "ru": "Используй YYYYMMDD или оставь пустым",
    "ua": "Використай YYYYMMDD або залиш порожнім"
  },
  "Pick date": {
    "ru": "Выбрать дату",
    "ua": "Обрати дату"
  },
  "Pick time": {
    "ru": "Выбрать время",
    "ua": "Обрати час"
  },
  "Clear field": {
    "ru": "Очистить поле",
    "ua": "Очистити поле"
  },
  "Tag dictionary": {
    "ru": "Справочник тегов",
    "ua": "Довідник тегів"
  },
  "No tags yet": {
    "ru": "Тегов пока нет",
    "ua": "Тегів поки немає"
  },
  "Close": {
    "ru": "Закрыть",
    "ua": "Закрити"
  },
  "Increase": {
    "ru": "Увеличить",
    "ua": "Збільшити"
  },
  "Decrease": {
    "ru": "Уменьшить",
    "ua": "Зменшити"
  },
  "One-time": {
    "ru": "Однократное",
    "ua": "Одноразове"
  },
  "Daily": {
    "ru": "Ежедневное",
    "ua": "Щоденне"
  },
  "Period": {
    "ru": "Период",
    "ua": "Період"
  },
  "Time": {
    "ru": "Время",
    "ua": "Час"
  },
  "Times": {
    "ru": "Времена",
    "ua": "Часи"
  },
  "Add time": {
    "ru": "Добавить время",
    "ua": "Додати час"
  },
  "No times yet": {
    "ru": "Времени пока нет",
    "ua": "Часу поки немає"
  },
  "Fullscreen alert": {
    "ru": "Полный экран",
    "ua": "Повний екран"
  },
  "Loop sound": {
    "ru": "Повтор звука",
    "ua": "Повтор звуку"
  },
  "Yearly repeat": {
    "ru": "Повторять ежегодно",
    "ua": "Повторювати щороку"
  },
  "Monthly repeat": {
    "ru": "Повторять ежемесячно",
    "ua": "Повторювати щомісяця"
  },
  "Auto-remove after firing": {
    "ru": "Удалить после срабатывания",
    "ua": "Видалити після спрацювання"
  },
  "Morning": {
    "ru": "Утро",
    "ua": "Ранок"
  },
  "Day": {
    "ru": "День",
    "ua": "День"
  },
  "Evening": {
    "ru": "Вечер",
    "ua": "Вечір"
  },
  "From": {
    "ru": "От",
    "ua": "Від"
  },
  "To": {
    "ru": "До",
    "ua": "До"
  },
  "Every day": {
    "ru": "Каждый день",
    "ua": "Щодня"
  },
  "Weekdays": {
    "ru": "Будни",
    "ua": "Будні"
  },
  "Weekend": {
    "ru": "Выходные",
    "ua": "Вихідні"
  },
  "Mon": {
    "ru": "Пн",
    "ua": "Пн"
  },
  "Tue": {
    "ru": "Вт",
    "ua": "Вт"
  },
  "Wed": {
    "ru": "Ср",
    "ua": "Ср"
  },
  "Thu": {
    "ru": "Чт",
    "ua": "Чт"
  },
  "Fri": {
    "ru": "Пт",
    "ua": "Пт"
  },
  "Sat": {
    "ru": "Сб",
    "ua": "Сб"
  },
  "Sun": {
    "ru": "Вс",
    "ua": "Нд"
  },
  "Mo": {
    "ru": "Пн",
    "ua": "Пн"
  },
  "Tu": {
    "ru": "Вт",
    "ua": "Вт"
  },
  "We": {
    "ru": "Ср",
    "ua": "Ср"
  },
  "Th": {
    "ru": "Чт",
    "ua": "Чт"
  },
  "Fr": {
    "ru": "Пт",
    "ua": "Пт"
  },
  "Sa": {
    "ru": "Сб",
    "ua": "Сб"
  },
  "Su": {
    "ru": "Нд",
    "ua": "Нд"
  },
  "Remove": {
    "ru": "Убрать",
    "ua": "Прибрати"
  },
  "Reminder date is required": {
    "ru": "Дата напоминания обязательна",
    "ua": "Дата нагадування обов'язкова"
  },
  "Reminder time is required": {
    "ru": "Время напоминания обязательно",
    "ua": "Час нагадування обов'язковий"
  },
  "Select at least one day": {
    "ru": "Выбери хотя бы один день",
    "ua": "Оберіть хоча б один день"
  },
  "Select at least one time": {
    "ru": "Выбери хотя бы одно время",
    "ua": "Оберіть хоча б один час"
  },
  "From date is required": {
    "ru": "Дата от обязательна",
    "ua": "Дата від обов'язкова"
  },
  "To date is required": {
    "ru": "Дата до обязательна",
    "ua": "Дата до обов'язкова"
  },
  "Both dates must be same format": {
    "ru": "Обе даты должны быть одного формата",
    "ua": "Обидві дати мають бути одного формату"
  },
  "From date must not be after To date": {
    "ru": "Дата от не должна быть позже даты до",
    "ua": "Дата від не повинна бути пізніше дати до"
  },
  "Priority high": {
    "ru": "Высокий приоритет",
    "ua": "Високий пріоритет"
  },
  "Enable for important memos": {
    "ru": "Включай для важных заметок",
    "ua": "Увімкни для важливих нотаток"
  },
  "Notes": {
    "ru": "Заметки",
    "ua": "Нотатки"
  },
  "Unchecked items": {
    "ru": "Активные элементы",
    "ua": "Активні елементи"
  },
  "Checked items": {
    "ru": "Выполненные элементы",
    "ua": "Виконані елементи"
  },
  "Loading items": {
    "ru": "Загрузка элементов",
    "ua": "Завантаження елементів"
  },
  "No active items": {
    "ru": "Активных элементов пока нет",
    "ua": "Активних елементів поки немає"
  },
  "Add the first item to this list.": {
    "ru": "Добавь первый элемент в этот список.",
    "ua": "Додай перший елемент у цей список."
  },
  "Daily Reminders": {
    "ru": "Ежедневные напоминания",
    "ua": "Щоденні нагадування"
  },
  "Periods": {
    "ru": "Периоды",
    "ua": "Періоди"
  },
  "Monthly Events": {
    "ru": "Ежемесячные события",
    "ua": "Щомісячні події"
  },
  "Yearly Events": {
    "ru": "Ежегодные события",
    "ua": "Щорічні події"
  },
  "Theme applied immediately": {
    "ru": "Тема применяется сразу",
    "ua": "Тема застосовується одразу"
  },
  "Reminders master switch": {
    "ru": "Главный переключатель напоминаний",
    "ua": "Головний перемикач нагадувань"
  },
  "Sort preference": {
    "ru": "Настройка сортировки",
    "ua": "Налаштування сортування"
  },
  "This screen is a starting scaffold.": {
    "ru": "Этот экран пока является стартовым каркасом.",
    "ua": "Цей екран поки є стартовим каркасом."
  },
  "Open memos module": {
    "ru": "Открыть модуль заметок",
    "ua": "Відкрити модуль нотаток"
  }
}
